[{"id":"20250920_95","preview":"game/20250920/95.png","download":"game/20250920/95.zip"},{"id":"20250920_94","preview":"game/20250920/94.png","download":"game/20250920/94.zip"},{"id":"20250920_93","preview":"game/20250920/93.png","download":"game/20250920/93.zip"},{"id":"20250920_92","preview":"game/20250920/92.png","download":"game/20250920/92.zip"},{"id":"20250920_91","preview":"game/20250920/91.png","download":"game/20250920/91.zip"},{"id":"20250920_90","preview":"game/20250920/90.png","download":"game/20250920/90.zip","reward":1}]